setup.py
pyDiameter/__init__.py
pyDiameter/pyDiaAVPBase.py
pyDiameter/pyDiaAVPBasicTypes.py
pyDiameter/pyDiaAVPBasicTypesConst.py
pyDiameter/pyDiaAVPConst.py
pyDiameter/pyDiaAVPDict.py
pyDiameter/pyDiaAVPFactory.py
pyDiameter/pyDiaAVPPath.py
pyDiameter/pyDiaAVPTools.py
pyDiameter/pyDiaAVPTypes.py
pyDiameter/pyDiaConst.py
pyDiameter/pyDiaMessage.py
pyDiameter/pyDiaMessageConst.py
pyDiameter.egg-info/PKG-INFO
pyDiameter.egg-info/SOURCES.txt
pyDiameter.egg-info/dependency_links.txt
pyDiameter.egg-info/top_level.txt
pyDiameter/examples/__init__.py
pyDiameter/examples/example-avp.py
pyDiameter/examples/example-dictTest.py
pyDiameter/examples/example-msg1.py